midi/__init__.py
midi/midi.py
midi/midiTypeMessage.py
midi/types.py
midi/utils.py
tests/__init__.py
tests/test_connector_object.py
tests/test_message_object.py
tests/test_message_types.py
py_midi-2.0.dist-info/LICENSE
py_midi-2.0.dist-info/METADATA
py_midi-2.0.dist-info/WHEEL
py_midi-2.0.dist-info/top_level.txt
py_midi-2.0.dist-info/RECORD
