Metadata-Version: 2.1
Name: py-midi
Version: 2.0
Summary: A package for sending and receiving MIDI messages easily.
Home-page: https://github.com/edouardtheron/py-midi
Author: Edouard Theron
Author-email: edouard@edtheron.me
License: GNU
Keywords: package library midi music digital serial interface
Platform: UNKNOWN
Classifier: Development Status :: 4 - Beta
Classifier: Intended Audience :: Developers
Classifier: License :: OSI Approved :: GNU General Public License (GPL)
Classifier: Topic :: Software Development :: Build Tools
Classifier: Programming Language :: Python :: 3
Classifier: Programming Language :: Python :: 3.3
Classifier: Programming Language :: Python :: 3.4
Classifier: Programming Language :: Python :: 3.5
Requires-Dist: pyserial
